fed_rag/__init__.py
fed_rag/__init__.pyi
fed_rag/_version.py
fed_rag/py.typed
fed_rag/_bridges/__init__.py
fed_rag/_bridges/langchain/__init__.py
fed_rag/_bridges/langchain/_bridge_classes.py
fed_rag/_bridges/langchain/_version.py
fed_rag/_bridges/langchain/bridge.py
fed_rag/_bridges/llamaindex/__init__.py
fed_rag/_bridges/llamaindex/_managed_index.py
fed_rag/_bridges/llamaindex/_version.py
fed_rag/_bridges/llamaindex/bridge.py
fed_rag/base/__init__.py
fed_rag/base/bridge.py
fed_rag/base/data_collator.py
fed_rag/base/fl_task.py
fed_rag/base/generator.py
fed_rag/base/knowledge_store.py
fed_rag/base/no_encode_knowledge_store.py
fed_rag/base/retriever.py
fed_rag/base/tokenizer.py
fed_rag/base/trainer.py
fed_rag/base/trainer_config.py
fed_rag/base/trainer_manager.py
fed_rag/base/evals/__init__.py
fed_rag/base/evals/benchmark.py
fed_rag/base/evals/metric.py
fed_rag/core/__init__.py
fed_rag/core/no_encode_rag_system/__init__.py
fed_rag/core/no_encode_rag_system/_asynchronous.py
fed_rag/core/no_encode_rag_system/_synchronous.py
fed_rag/core/no_encode_rag_system/asynchronous.py
fed_rag/core/no_encode_rag_system/synchronous.py
fed_rag/core/rag_system/__init__.py
fed_rag/core/rag_system/_asynchronous.py
fed_rag/core/rag_system/_synchronous.py
fed_rag/core/rag_system/asynchronous.py
fed_rag/core/rag_system/synchronous.py
fed_rag/data_collators/__init__.py
fed_rag/data_collators/huggingface/__init__.py
fed_rag/data_collators/huggingface/lsr.py
fed_rag/data_collators/huggingface/ralt.py
fed_rag/data_structures/__init__.py
fed_rag/data_structures/bridge.py
fed_rag/data_structures/evals.py
fed_rag/data_structures/knowledge_node.py
fed_rag/data_structures/rag.py
fed_rag/data_structures/results.py
fed_rag/decorators/__init__.py
fed_rag/decorators/tester.py
fed_rag/decorators/trainer.py
fed_rag/evals/__init__.py
fed_rag/evals/benchmarker.py
fed_rag/evals/utils.py
fed_rag/evals/benchmarks/__init__.py
fed_rag/evals/benchmarks/huggingface/__init__.py
fed_rag-0.0.27.dist-info/METADATA
fed_rag-0.0.27.dist-info/WHEEL
fed_rag-0.0.27.dist-info/licenses/LICENSE
fed_rag-0.0.27.dist-info/RECORD
