Metadata-Version: 2.4
Name: fed-rag
Version: 0.0.27
Summary: Simplified fine-tuning of retrieval-augmented generation (RAG) systems.
Project-URL: Documentation, https://vectorinstitute.github.io/fed-rag/
Project-URL: Repository, https://github.com/VectorInstitute/fed-rag
Project-URL: Issues, https://github.com/VectorInstitute/fed-rag/issues
Project-URL: Changelog, https://github.com/VectorInstitute/fed-rag/blob/main/CHANGELOG.md
Author-email: Andrei Fajardo <andrei.fajardo@vectorinstitute.ai>, David Emerson <david.emerson@vectorinstitute.ai>
Maintainer-email: Andrei Fajardo <andrei.fajardo@vectorinstitute.ai>
License-Expression: Apache-2.0
License-File: LICENSE
Keywords: deep learning,federated learning,llms,machine learning,rag,retrieval,semantic search
Requires-Python: <4.0,>=3.10
Requires-Dist: datasets>=3.1.0
Requires-Dist: flwr>=1.18.0
Requires-Dist: mcp[cli]>=1.9.1
Requires-Dist: pyarrow>=19.0.1
Requires-Dist: pydantic-settings>=2.7.1
Requires-Dist: pydantic>=2.10.5
Requires-Dist: torch>=2.5.1
Requires-Dist: torchvision>=0.20.1
Requires-Dist: typing-extensions>=4.12.2
Provides-Extra: huggingface
Requires-Dist: peft>=0.14.0; extra == 'huggingface'
Requires-Dist: sentence-transformers>=3.4.1; extra == 'huggingface'
Requires-Dist: transformers>=4.49.0; extra == 'huggingface'
Provides-Extra: huggingface-evals
Requires-Dist: datasets>=3.1.0; extra == 'huggingface-evals'
Provides-Extra: langchain
Requires-Dist: langchain-core>=0.3.62; extra == 'langchain'
Provides-Extra: llama-index
Requires-Dist: llama-index-core>=0.12.35; extra == 'llama-index'
Provides-Extra: qdrant
Requires-Dist: grpcio>=1.71.0; extra == 'qdrant'
Requires-Dist: qdrant-client[fastembed]>=1.14.2; extra == 'qdrant'
Provides-Extra: unsloth
Requires-Dist: peft>=0.14.0; extra == 'unsloth'
Requires-Dist: sentence-transformers>=3.4.1; extra == 'unsloth'
Requires-Dist: transformers>=4.49.0; extra == 'unsloth'
Requires-Dist: unsloth>=2024.8; extra == 'unsloth'
